{
  "categories": [
    {
      "name": "creative",
      "title": "Creative",
      "description": "Prompts for creative writing, storytelling, and artistic endeavors",
      "icon": "🎨",
      "path": "src/prompts/creative/",
      "promptTypes": [
        {
          "type": "system",
          "file": "system-prompts.md",
          "description": "AI personality and creative assistant configurations"
        },
        {
          "type": "developer", 
          "file": "developer-prompts.md",
          "description": "Code generation for creative applications"
        },
        {
          "type": "user",
          "file": "user-prompts.md", 
          "description": "Creative writing, storytelling, and artistic endeavors"
        }
      ]
    },
    {
      "name": "technical",
      "title": "Technical",
      "description": "Programming, debugging, and technical documentation prompts",
      "icon": "🔧",
      "path": "src/prompts/technical/",
      "promptTypes": [
        {
          "type": "system",
          "file": "system-prompts.md",
          "description": "Technical expert and coding assistant configurations"
        },
        {
          "type": "developer",
          "file": "developer-prompts.md", 
          "description": "Programming, debugging, and development workflows"
        },
        {
          "type": "user",
          "file": "user-prompts.md",
          "description": "Technical documentation and problem-solving"
        }
      ]
    },
    {
      "name": "general",
      "title": "General",
      "description": "Everyday prompts for general AI assistance",
      "icon": "📋",
      "path": "src/prompts/general/",
      "promptTypes": [
        {
          "type": "system",
          "file": "system-prompts.md",
          "description": "General-purpose AI assistant configurations"
        },
        {
          "type": "developer",
          "file": "developer-prompts.md",
          "description": "Utility functions and general development tasks"
        },
        {
          "type": "user", 
          "file": "user-prompts.md",
          "description": "Everyday AI assistance and general inquiries"
        }
      ]
    },
    {
      "name": "agentic",
      "title": "Agentic",
      "description": "Prompts for AI agents and autonomous task completion",
      "icon": "🤖",
      "path": "src/prompts/agentic/",
      "promptTypes": [
        {
          "type": "system",
          "file": "system-prompts.md",
          "description": "Autonomous agent behavior and decision-making"
        },
        {
          "type": "developer",
          "file": "developer-prompts.md",
          "description": "Agent architecture and multi-step workflows"
        },
        {
          "type": "user",
          "file": "user-prompts.md",
          "description": "Task automation and goal-oriented interactions"
        }
      ]
    },
    {
      "name": "professional",
      "title": "Professional", 
      "description": "Business, workplace, and professional communication prompts",
      "icon": "💼",
      "path": "src/prompts/professional/",
      "promptTypes": [
        {
          "type": "system",
          "file": "system-prompts.md",
          "description": "Business and workplace AI assistant configurations"
        },
        {
          "type": "developer",
          "file": "developer-prompts.md",
          "description": "Enterprise development and workflow automation"
        },
        {
          "type": "user",
          "file": "user-prompts.md",
          "description": "Business communication and professional tasks"
        }
      ]
    }
  ],
  "metadata": {
    "version": "1.0.0",
    "totalCategories": 5,
    "promptTypesPerCategory": 3,
    "lastUpdated": "2025-06-03"
  }
}
